LICENSE
MANIFEST.in
README.rst
requirements.txt
setup.py
django_cryptocoin/__init__.py
django_cryptocoin/models.py
django_cryptocoin/settings.py
django_cryptocoin/signals.py
django_cryptocoin/urls.py
django_cryptocoin/views.py
django_cryptocoin.egg-info/PKG-INFO
django_cryptocoin.egg-info/SOURCES.txt
django_cryptocoin.egg-info/dependency_links.txt
django_cryptocoin.egg-info/top_level.txt
django_cryptocoin/bitcoinrpc/__init__.py
django_cryptocoin/bitcoinrpc/authproxy.py
django_cryptocoin/management/__init__.py
django_cryptocoin/management/commands/__init__.py
django_cryptocoin/management/commands/check_incomings.py
django_cryptocoin/management/commands/get_exchange_rates.py
django_cryptocoin/migrations/0001_initial.py
django_cryptocoin/migrations/__init__.py
django_cryptocoin/templates/django_cryptocoin/process.html